mdata/__init__.py
mdata/analysis/__init__.py
mdata/analysis/frequency.py
mdata/analysis/nan.py
mdata/analysis/segmentation/__init__.py
mdata/analysis/segmentation/detect_milling_engagagement.py
mdata/analysis/segmentation/interface.py
mdata/conversions/__init__.py
mdata/conversions/conversion_utils.py
mdata/conversions/ocel/__init__.py
mdata/conversions/ocel/ocel_export.py
mdata/core/__init__.py
mdata/core/base_machine_data.py
mdata/core/df_utils.py
mdata/core/extensions/__init__.py
mdata/core/extensions/directionality/__init__.py
mdata/core/extensions/directionality/directions.py
mdata/core/extensions/metadata/__init__.py
mdata/core/extensions/metadata/feature_typing.py
mdata/core/extensions/multiplicity.py.txt
mdata/core/extensions/registry.py
mdata/core/extensions/segments/__init__.py
mdata/core/extensions/segments/properties.py
mdata/core/factory/__init__.py
mdata/core/factory/base.py
mdata/core/factory/casting.py
mdata/core/factory/factories.py
mdata/core/factory/factories_v2.py
mdata/core/factory/instance.py
mdata/core/header.py
mdata/core/protocols.py
mdata/core/raw.py
mdata/core/shared_defs.py
mdata/core/shared_protocols.py
mdata/core/util.py
mdata/core/v2/__init__.py
mdata/core/v2/header_v2.py
mdata/core/v2/machine_data_v2.py
mdata/core/v2/protocols_v2.py
mdata/core/v2/raw_v2.py
mdata/core/v2/shared_defs.py
mdata/core/v2/util.py
mdata/file_formats/__init__.py
mdata/file_formats/csv/__init__.py
mdata/file_formats/csv/checking.py
mdata/file_formats/csv/exporting.py
mdata/file_formats/csv/importing.py
mdata/file_formats/csv/v2/__init__.py
mdata/file_formats/csv/v2/exporting.py
mdata/file_formats/csv/v2/importing.py
mdata/file_formats/formats.py
mdata/file_formats/hdf/__init__.py
mdata/file_formats/hdf/checking.py
mdata/file_formats/hdf/exporting.py
mdata/file_formats/hdf/importing.py
mdata/file_formats/header_schema.json
mdata/file_formats/header_schema_v2.json
mdata/file_formats/io_utils.py
mdata/file_formats/schema_template.json
mdata/file_formats/shared.py
mdata-0.3.7.dist-info/METADATA
mdata-0.3.7.dist-info/WHEEL
mdata-0.3.7.dist-info/RECORD
