Metadata-Version: 2.1
Name: mdata
Version: 0.3.7
Summary: 
License: MIT
Keywords: data format,machine data
Author: Leah Tacke genannt Unterberg
Author-email: leah.tgu@pads.rwth-aachen.de
Requires-Python: >=3.11,<3.13
Classifier: License :: OSI Approved :: MIT License
Classifier: Programming Language :: Python :: 3
Classifier: Programming Language :: Python :: 3.11
Classifier: Programming Language :: Python :: 3.12
Requires-Dist: immutabledict
Requires-Dist: matplotlib
Requires-Dist: numpy (>=2.0,<3.0)
Requires-Dist: pandas[compression,computation,excel,hdf5,output-formatting,performance,plot] (>=2.0,<3.0)
Requires-Dist: plotly (>=5.24.0,<6.0.0)
Requires-Dist: pm4py (>=2.7.0,<3.0.0)
Requires-Dist: pyyaml
Requires-Dist: seaborn
